tailnet_admin/__init__.py
tailnet_admin/api.py
tailnet_admin/cli.py
tailnet_admin/models.py
tailnet_admin/tag_cli.py
tailnet_admin/tags.py
tailnet_admin_cli-0.1.0.dist-info/METADATA
tailnet_admin_cli-0.1.0.dist-info/WHEEL
tailnet_admin_cli-0.1.0.dist-info/entry_points.txt
tailnet_admin_cli-0.1.0.dist-info/RECORD
