Metadata-Version: 2.4
Name: tailnet-admin-cli
Version: 0.1.0
Summary: Tailscale Tailnet administration CLI tool
Requires-Python: >=3.10
Requires-Dist: authlib>=1.3.0
Requires-Dist: httpx>=0.26.0
Requires-Dist: keyring>=24.3.0
Requires-Dist: pydantic>=2.5.0
Requires-Dist: rich>=13.7.0
Requires-Dist: typer>=0.9.0
